gpt_commands/__init__.py
gpt_commands/client.py
gpt_commands/introspection.py
gpt_commands/utils.py
gpt_commands_python-0.1.0.dist-info/LICENSE.txt
gpt_commands_python-0.1.0.dist-info/METADATA
gpt_commands_python-0.1.0.dist-info/WHEEL
gpt_commands_python-0.1.0.dist-info/top_level.txt
gpt_commands_python-0.1.0.dist-info/RECORD
