Metadata-Version: 2.1
Name: gpt-commands-python
Version: 0.1.0
Summary: A python module that provides an easy way to use OpenAI GPT-4 (or 3.5) function calling
Home-page: https://github.com/keenua/gpt-commands-python
Author: Roman Olshevskyi
Author-email: gpt.commands.python@gmail.com
Project-URL: Bug Tracker, https://github.com/keenua/gpt-commands-python/issues
Classifier: Programming Language :: Python :: 3
Classifier: License :: OSI Approved :: MIT License
Classifier: Operating System :: OS Independent
Requires-Python: >=3.8
License-File: LICENSE.txt
Requires-Dist: aiohttp (>=3.8.3)
Requires-Dist: python-dotenv (>=0.21.0)
Requires-Dist: docstring-parser (>=0.15)
Requires-Dist: dataclasses-json (>=0.5.7)
Requires-Dist: dataclasses-jsonschema (>=2.16.0)
